{
  "id": "chuoichienhfb",
  "url": "https://hfbtv.vercel.app/chuoichientv.json",
  "name": "Chuối Chiên TV",
  "color": "#003A17",
  "description": "Cập nhật trực tiếp từ Chuối Chiên TV",
  "image": {
    "url": "https://raw.githubusercontent.com/nghehoang007-wq/HFB321/main/HFB/Thump/chuoichien.png"
  },
  "groups": [
    {
      "id": "live",
      "name": "🔴 TRỰC TIẾP CHUỐI CHIÊN",
      "display": "vertical",
      "grid_number": 2,
      "channels": [
        {
          "id": "6a25012909ffd978546c2ece",
          "name": "Peru vs Spain",
          "labels": [
            {
              "position": "bottom-center",
              "text": "09h00",
              "color": "#FF0000",
              "text_color": "#FFFFFF"
            },
            {
              "position": "top-left",
              "text": "Peru",
              "color": "#80000000",
              "text_color": "#FFFFFF"
            },
            {
              "position": "top-right",
              "text": "Spain",
              "color": "#80000000",
              "text_color": "#FFFFFF"
            }
          ],
          "image": {
            "url": "https://raw.githubusercontent.com/nghehoang007-wq/HFB321/main/thumbs/6a25012909ffd978546c2ece.png",
            "height": 360,
            "width": 640,
            "display": "cover"
          },
          "type": "single",
          "display": "thumbnail-only",
          "sources": [
            {
              "id": "src-6a25012909ffd978546c2ece",
              "name": "Chuối Chiên",
              "contents": [
                {
                  "id": "c-6a25012909ffd978546c2ece",
                  "name": "Peru vs Spain",
                  "streams": [
                    {
                      "id": "6a25012909ffd978546c2ece_0",
                      "name": "Cậu Cả - HD1",
                      "remote_data": {
                        "url": "https://raw.githubusercontent.com/nghehoang007-wq/HFB321/main/stream/6a25012909ffd978546c2ece.json"
                      }
                    },
                    {
                      "id": "6a25012909ffd978546c2ece_1",
                      "name": "Cậu Cả - HD2",
                      "remote_data": {
                        "url": "https://raw.githubusercontent.com/nghehoang007-wq/HFB321/main/stream/6a25012909ffd978546c2ece.json"
                      }
                    },
                    {
                      "id": "6a25012909ffd978546c2ece_2",
                      "name": "Cậu Cả - FHD1",
                      "remote_data": {
                        "url": "https://raw.githubusercontent.com/nghehoang007-wq/HFB321/main/stream/6a25012909ffd978546c2ece.json"
                      }
                    },
                    {
                      "id": "6a25012909ffd978546c2ece_3",
                      "name": "Cậu Cả - FHD2",
                      "remote_data": {
                        "url": "https://raw.githubusercontent.com/nghehoang007-wq/HFB321/main/stream/6a25012909ffd978546c2ece.json"
                      }
                    }
                  ]
                }
              ]
            }
          ]
        },
        {
          "id": "6a2452a8c3ee3a60ffc9b9ef",
          "name": "Lebanon W vs Iran W",
          "labels": [
            {
              "position": "bottom-center",
              "text": "11h00",
              "color": "#FF0000",
              "text_color": "#FFFFFF"
            },
            {
              "position": "top-left",
              "text": "Lebanon W",
              "color": "#80000000",
              "text_color": "#FFFFFF"
            },
            {
              "position": "top-right",
              "text": "Iran W",
              "color": "#80000000",
              "text_color": "#FFFFFF"
            }
          ],
          "image": {
            "url": "https://raw.githubusercontent.com/nghehoang007-wq/HFB321/main/thumbs/6a2452a8c3ee3a60ffc9b9ef.png",
            "height": 360,
            "width": 640,
            "display": "cover"
          },
          "type": "single",
          "display": "thumbnail-only",
          "sources": [
            {
              "id": "src-6a2452a8c3ee3a60ffc9b9ef",
              "name": "Chuối Chiên",
              "contents": [
                {
                  "id": "c-6a2452a8c3ee3a60ffc9b9ef",
                  "name": "Lebanon W vs Iran W",
                  "streams": [
                    {
                      "id": "6a2452a8c3ee3a60ffc9b9ef_0",
                      "name": "Chuối Tây - HD1",
                      "remote_data": {
                        "url": "https://raw.githubusercontent.com/nghehoang007-wq/HFB321/main/stream/6a2452a8c3ee3a60ffc9b9ef.json"
                      }
                    },
                    {
                      "id": "6a2452a8c3ee3a60ffc9b9ef_1",
                      "name": "Chuối Tây - HD2",
                      "remote_data": {
                        "url": "https://raw.githubusercontent.com/nghehoang007-wq/HFB321/main/stream/6a2452a8c3ee3a60ffc9b9ef.json"
                      }
                    },
                    {
                      "id": "6a2452a8c3ee3a60ffc9b9ef_2",
                      "name": "Chuối Tây - FHD1",
                      "remote_data": {
                        "url": "https://raw.githubusercontent.com/nghehoang007-wq/HFB321/main/stream/6a2452a8c3ee3a60ffc9b9ef.json"
                      }
                    },
                    {
                      "id": "6a2452a8c3ee3a60ffc9b9ef_3",
                      "name": "Chuối Tây - FHD2",
                      "remote_data": {
                        "url": "https://raw.githubusercontent.com/nghehoang007-wq/HFB321/main/stream/6a2452a8c3ee3a60ffc9b9ef.json"
                      }
                    }
                  ]
                }
              ]
            }
          ]
        },
        {
          "id": "6a2452c53f7d141c5a986664",
          "name": "Uzbekistan W vs Chinese Taipei W",
          "labels": [
            {
              "position": "bottom-center",
              "text": "11h00",
              "color": "#FF0000",
              "text_color": "#FFFFFF"
            },
            {
              "position": "top-left",
              "text": "Uzbekistan W",
              "color": "#80000000",
              "text_color": "#FFFFFF"
            },
            {
              "position": "top-right",
              "text": "Chinese Taip..",
              "color": "#80000000",
              "text_color": "#FFFFFF"
            }
          ],
          "image": {
            "url": "https://raw.githubusercontent.com/nghehoang007-wq/HFB321/main/thumbs/6a2452c53f7d141c5a986664.png",
            "height": 360,
            "width": 640,
            "display": "cover"
          },
          "type": "single",
          "display": "thumbnail-only",
          "sources": [
            {
              "id": "src-6a2452c53f7d141c5a986664",
              "name": "Chuối Chiên",
              "contents": [
                {
                  "id": "c-6a2452c53f7d141c5a986664",
                  "name": "Uzbekistan W vs Chinese Taipei W",
                  "streams": [
                    {
                      "id": "6a2452c53f7d141c5a986664_0",
                      "name": "Chuối Tím - HD1",
                      "remote_data": {
                        "url": "https://raw.githubusercontent.com/nghehoang007-wq/HFB321/main/stream/6a2452c53f7d141c5a986664.json"
                      }
                    },
                    {
                      "id": "6a2452c53f7d141c5a986664_1",
                      "name": "Chuối Tím - HD2",
                      "remote_data": {
                        "url": "https://raw.githubusercontent.com/nghehoang007-wq/HFB321/main/stream/6a2452c53f7d141c5a986664.json"
                      }
                    },
                    {
                      "id": "6a2452c53f7d141c5a986664_2",
                      "name": "Chuối Tím - FHD1",
                      "remote_data": {
                        "url": "https://raw.githubusercontent.com/nghehoang007-wq/HFB321/main/stream/6a2452c53f7d141c5a986664.json"
                      }
                    },
                    {
                      "id": "6a2452c53f7d141c5a986664_3",
                      "name": "Chuối Tím - FHD2",
                      "remote_data": {
                        "url": "https://raw.githubusercontent.com/nghehoang007-wq/HFB321/main/stream/6a2452c53f7d141c5a986664.json"
                      }
                    }
                  ]
                }
              ]
            }
          ]
        },
        {
          "id": "6a2452f252cb617cc79f90d9",
          "name": "Philippines W vs South Korea W",
          "labels": [
            {
              "position": "bottom-center",
              "text": "14h00",
              "color": "#FF0000",
              "text_color": "#FFFFFF"
            },
            {
              "position": "top-left",
              "text": "Philippines W",
              "color": "#80000000",
              "text_color": "#FFFFFF"
            },
            {
              "position": "top-right",
              "text": "South Korea W",
              "color": "#80000000",
              "text_color": "#FFFFFF"
            }
          ],
          "image": {
            "url": "https://raw.githubusercontent.com/nghehoang007-wq/HFB321/main/thumbs/6a2452f252cb617cc79f90d9.png",
            "height": 360,
            "width": 640,
            "display": "cover"
          },
          "type": "single",
          "display": "thumbnail-only",
          "sources": [
            {
              "id": "src-6a2452f252cb617cc79f90d9",
              "name": "Chuối Chiên",
              "contents": [
                {
                  "id": "c-6a2452f252cb617cc79f90d9",
                  "name": "Philippines W vs South Korea W",
                  "streams": [
                    {
                      "id": "6a2452f252cb617cc79f90d9_0",
                      "name": "Chuối Bơ - HD1",
                      "remote_data": {
                        "url": "https://raw.githubusercontent.com/nghehoang007-wq/HFB321/main/stream/6a2452f252cb617cc79f90d9.json"
                      }
                    },
                    {
                      "id": "6a2452f252cb617cc79f90d9_1",
                      "name": "Chuối Bơ - HD2",
                      "remote_data": {
                        "url": "https://raw.githubusercontent.com/nghehoang007-wq/HFB321/main/stream/6a2452f252cb617cc79f90d9.json"
                      }
                    },
                    {
                      "id": "6a2452f252cb617cc79f90d9_2",
                      "name": "Chuối Bơ - FHD1",
                      "remote_data": {
                        "url": "https://raw.githubusercontent.com/nghehoang007-wq/HFB321/main/stream/6a2452f252cb617cc79f90d9.json"
                      }
                    },
                    {
                      "id": "6a2452f252cb617cc79f90d9_3",
                      "name": "Chuối Bơ - FHD2",
                      "remote_data": {
                        "url": "https://raw.githubusercontent.com/nghehoang007-wq/HFB321/main/stream/6a2452f252cb617cc79f90d9.json"
                      }
                    }
                  ]
                }
              ]
            }
          ]
        },
        {
          "id": "6a25012909ffd978546c2ee0",
          "name": "Timor-Leste vs Brunei",
          "labels": [
            {
              "position": "bottom-center",
              "text": "16h00",
              "color": "#FF0000",
              "text_color": "#FFFFFF"
            },
            {
              "position": "top-left",
              "text": "Timor-Leste",
              "color": "#80000000",
              "text_color": "#FFFFFF"
            },
            {
              "position": "top-right",
              "text": "Brunei",
              "color": "#80000000",
              "text_color": "#FFFFFF"
            }
          ],
          "image": {
            "url": "https://raw.githubusercontent.com/nghehoang007-wq/HFB321/main/thumbs/6a25012909ffd978546c2ee0.png",
            "height": 360,
            "width": 640,
            "display": "cover"
          },
          "type": "single",
          "display": "thumbnail-only",
          "sources": [
            {
              "id": "src-6a25012909ffd978546c2ee0",
              "name": "Chuối Chiên",
              "contents": [
                {
                  "id": "c-6a25012909ffd978546c2ee0",
                  "name": "Timor-Leste vs Brunei",
                  "streams": [
                    {
                      "id": "6a25012909ffd978546c2ee0_0",
                      "name": "Trốc Tru - HD1",
                      "remote_data": {
                        "url": "https://raw.githubusercontent.com/nghehoang007-wq/HFB321/main/stream/6a25012909ffd978546c2ee0.json"
                      }
                    },
                    {
                      "id": "6a25012909ffd978546c2ee0_1",
                      "name": "Trốc Tru - HD2",
                      "remote_data": {
                        "url": "https://raw.githubusercontent.com/nghehoang007-wq/HFB321/main/stream/6a25012909ffd978546c2ee0.json"
                      }
                    },
                    {
                      "id": "6a25012909ffd978546c2ee0_2",
                      "name": "Trốc Tru - FHD1",
                      "remote_data": {
                        "url": "https://raw.githubusercontent.com/nghehoang007-wq/HFB321/main/stream/6a25012909ffd978546c2ee0.json"
                      }
                    },
                    {
                      "id": "6a25012909ffd978546c2ee0_3",
                      "name": "Trốc Tru - FHD2",
                      "remote_data": {
                        "url": "https://raw.githubusercontent.com/nghehoang007-wq/HFB321/main/stream/6a25012909ffd978546c2ee0.json"
                      }
                    }
                  ]
                }
              ]
            }
          ]
        },
        {
          "id": "6a245314966a612324c163f1",
          "name": "Hong Kong W vs Indonesia W",
          "labels": [
            {
              "position": "bottom-center",
              "text": "17h00",
              "color": "#FF0000",
              "text_color": "#FFFFFF"
            },
            {
              "position": "top-left",
              "text": "Hong Kong W",
              "color": "#80000000",
              "text_color": "#FFFFFF"
            },
            {
              "position": "top-right",
              "text": "Indonesia W",
              "color": "#80000000",
              "text_color": "#FFFFFF"
            }
          ],
          "image": {
            "url": "https://raw.githubusercontent.com/nghehoang007-wq/HFB321/main/thumbs/6a245314966a612324c163f1.png",
            "height": 360,
            "width": 640,
            "display": "cover"
          },
          "type": "single",
          "display": "thumbnail-only",
          "sources": [
            {
              "id": "src-6a245314966a612324c163f1",
              "name": "Chuối Chiên",
              "contents": [
                {
                  "id": "c-6a245314966a612324c163f1",
                  "name": "Hong Kong W vs Indonesia W",
                  "streams": [
                    {
                      "id": "6a245314966a612324c163f1_0",
                      "name": "Chuối Tím - HD1",
                      "remote_data": {
                        "url": "https://raw.githubusercontent.com/nghehoang007-wq/HFB321/main/stream/6a245314966a612324c163f1.json"
                      }
                    },
                    {
                      "id": "6a245314966a612324c163f1_1",
                      "name": "Chuối Tím - HD2",
                      "remote_data": {
                        "url": "https://raw.githubusercontent.com/nghehoang007-wq/HFB321/main/stream/6a245314966a612324c163f1.json"
                      }
                    },
                    {
                      "id": "6a245314966a612324c163f1_2",
                      "name": "Chuối Tím - FHD1",
                      "remote_data": {
                        "url": "https://raw.githubusercontent.com/nghehoang007-wq/HFB321/main/stream/6a245314966a612324c163f1.json"
                      }
                    },
                    {
                      "id": "6a245314966a612324c163f1_3",
                      "name": "Chuối Tím - FHD2",
                      "remote_data": {
                        "url": "https://raw.githubusercontent.com/nghehoang007-wq/HFB321/main/stream/6a245314966a612324c163f1.json"
                      }
                    }
                  ]
                }
              ]
            }
          ]
        },
        {
          "id": "6a25012909ffd978546c2eda",
          "name": "U23 Thailand  vs UAE U23",
          "labels": [
            {
              "position": "bottom-center",
              "text": "17h00",
              "color": "#FF0000",
              "text_color": "#FFFFFF"
            },
            {
              "position": "top-left",
              "text": "U23 Thailand",
              "color": "#80000000",
              "text_color": "#FFFFFF"
            },
            {
              "position": "top-right",
              "text": "UAE U23",
              "color": "#80000000",
              "text_color": "#FFFFFF"
            }
          ],
          "image": {
            "url": "https://raw.githubusercontent.com/nghehoang007-wq/HFB321/main/thumbs/6a25012909ffd978546c2eda.png",
            "height": 360,
            "width": 640,
            "display": "cover"
          },
          "type": "single",
          "display": "thumbnail-only",
          "sources": [
            {
              "id": "src-6a25012909ffd978546c2eda",
              "name": "Chuối Chiên",
              "contents": [
                {
                  "id": "c-6a25012909ffd978546c2eda",
                  "name": "U23 Thailand  vs UAE U23",
                  "streams": [
                    {
                      "id": "6a25012909ffd978546c2eda_0",
                      "name": "Chuối Nhỏ - HD1",
                      "remote_data": {
                        "url": "https://raw.githubusercontent.com/nghehoang007-wq/HFB321/main/stream/6a25012909ffd978546c2eda.json"
                      }
                    },
                    {
                      "id": "6a25012909ffd978546c2eda_1",
                      "name": "Chuối Nhỏ - HD2",
                      "remote_data": {
                        "url": "https://raw.githubusercontent.com/nghehoang007-wq/HFB321/main/stream/6a25012909ffd978546c2eda.json"
                      }
                    },
                    {
                      "id": "6a25012909ffd978546c2eda_2",
                      "name": "Chuối Nhỏ - FHD1",
                      "remote_data": {
                        "url": "https://raw.githubusercontent.com/nghehoang007-wq/HFB321/main/stream/6a25012909ffd978546c2eda.json"
                      }
                    },
                    {
                      "id": "6a25012909ffd978546c2eda_3",
                      "name": "Chuối Nhỏ - FHD2",
                      "remote_data": {
                        "url": "https://raw.githubusercontent.com/nghehoang007-wq/HFB321/main/stream/6a25012909ffd978546c2eda.json"
                      }
                    }
                  ]
                }
              ]
            }
          ]
        },
        {
          "id": "6a25012909ffd978546c2ed7",
          "name": "Philippines vs Myanmar",
          "labels": [
            {
              "position": "bottom-center",
              "text": "18h30",
              "color": "#FF0000",
              "text_color": "#FFFFFF"
            },
            {
              "position": "top-left",
              "text": "Philippines",
              "color": "#80000000",
              "text_color": "#FFFFFF"
            },
            {
              "position": "top-right",
              "text": "Myanmar",
              "color": "#80000000",
              "text_color": "#FFFFFF"
            }
          ],
          "image": {
            "url": "https://raw.githubusercontent.com/nghehoang007-wq/HFB321/main/thumbs/6a25012909ffd978546c2ed7.png",
            "height": 360,
            "width": 640,
            "display": "cover"
          },
          "type": "single",
          "display": "thumbnail-only",
          "sources": [
            {
              "id": "src-6a25012909ffd978546c2ed7",
              "name": "Chuối Chiên",
              "contents": [
                {
                  "id": "c-6a25012909ffd978546c2ed7",
                  "name": "Philippines vs Myanmar",
                  "streams": [
                    {
                      "id": "6a25012909ffd978546c2ed7_0",
                      "name": "Trốc Tru - HD1",
                      "remote_data": {
                        "url": "https://raw.githubusercontent.com/nghehoang007-wq/HFB321/main/stream/6a25012909ffd978546c2ed7.json"
                      }
                    },
                    {
                      "id": "6a25012909ffd978546c2ed7_1",
                      "name": "Trốc Tru - HD2",
                      "remote_data": {
                        "url": "https://raw.githubusercontent.com/nghehoang007-wq/HFB321/main/stream/6a25012909ffd978546c2ed7.json"
                      }
                    },
                    {
                      "id": "6a25012909ffd978546c2ed7_2",
                      "name": "Trốc Tru - FHD1",
                      "remote_data": {
                        "url": "https://raw.githubusercontent.com/nghehoang007-wq/HFB321/main/stream/6a25012909ffd978546c2ed7.json"
                      }
                    },
                    {
                      "id": "6a25012909ffd978546c2ed7_3",
                      "name": "Trốc Tru - FHD2",
                      "remote_data": {
                        "url": "https://raw.githubusercontent.com/nghehoang007-wq/HFB321/main/stream/6a25012909ffd978546c2ed7.json"
                      }
                    }
                  ]
                }
              ]
            }
          ]
        },
        {
          "id": "6a25012909ffd978546c2ed9",
          "name": "China vs Thailand",
          "labels": [
            {
              "position": "bottom-center",
              "text": "18h35",
              "color": "#FF0000",
              "text_color": "#FFFFFF"
            },
            {
              "position": "top-left",
              "text": "China",
              "color": "#80000000",
              "text_color": "#FFFFFF"
            },
            {
              "position": "top-right",
              "text": "Thailand",
              "color": "#80000000",
              "text_color": "#FFFFFF"
            }
          ],
          "image": {
            "url": "https://raw.githubusercontent.com/nghehoang007-wq/HFB321/main/thumbs/6a25012909ffd978546c2ed9.png",
            "height": 360,
            "width": 640,
            "display": "cover"
          },
          "type": "single",
          "display": "thumbnail-only",
          "sources": [
            {
              "id": "src-6a25012909ffd978546c2ed9",
              "name": "Chuối Chiên",
              "contents": [
                {
                  "id": "c-6a25012909ffd978546c2ed9",
                  "name": "China vs Thailand",
                  "streams": [
                    {
                      "id": "6a25012909ffd978546c2ed9_0",
                      "name": "Chuối Chao - HD1",
                      "remote_data": {
                        "url": "https://raw.githubusercontent.com/nghehoang007-wq/HFB321/main/stream/6a25012909ffd978546c2ed9.json"
                      }
                    },
                    {
                      "id": "6a25012909ffd978546c2ed9_1",
                      "name": "Chuối Chao - HD2",
                      "remote_data": {
                        "url": "https://raw.githubusercontent.com/nghehoang007-wq/HFB321/main/stream/6a25012909ffd978546c2ed9.json"
                      }
                    },
                    {
                      "id": "6a25012909ffd978546c2ed9_2",
                      "name": "Chuối Chao - FHD1",
                      "remote_data": {
                        "url": "https://raw.githubusercontent.com/nghehoang007-wq/HFB321/main/stream/6a25012909ffd978546c2ed9.json"
                      }
                    },
                    {
                      "id": "6a25012909ffd978546c2ed9_3",
                      "name": "Chuối Chao - FHD2",
                      "remote_data": {
                        "url": "https://raw.githubusercontent.com/nghehoang007-wq/HFB321/main/stream/6a25012909ffd978546c2ed9.json"
                      }
                    }
                  ]
                }
              ]
            }
          ]
        },
        {
          "id": "6a25012909ffd978546c2ed1",
          "name": "Cambodia vs Hong Kong",
          "labels": [
            {
              "position": "bottom-center",
              "text": "19h00",
              "color": "#FF0000",
              "text_color": "#FFFFFF"
            },
            {
              "position": "top-left",
              "text": "Cambodia",
              "color": "#80000000",
              "text_color": "#FFFFFF"
            },
            {
              "position": "top-right",
              "text": "Hong Kong",
              "color": "#80000000",
              "text_color": "#FFFFFF"
            }
          ],
          "image": {
            "url": "https://raw.githubusercontent.com/nghehoang007-wq/HFB321/main/thumbs/6a25012909ffd978546c2ed1.png",
            "height": 360,
            "width": 640,
            "display": "cover"
          },
          "type": "single",
          "display": "thumbnail-only",
          "sources": [
            {
              "id": "src-6a25012909ffd978546c2ed1",
              "name": "Chuối Chiên",
              "contents": [
                {
                  "id": "c-6a25012909ffd978546c2ed1",
                  "name": "Cambodia vs Hong Kong",
                  "streams": [
                    {
                      "id": "6a25012909ffd978546c2ed1_0",
                      "name": "Chuối To - HD1",
                      "remote_data": {
                        "url": "https://raw.githubusercontent.com/nghehoang007-wq/HFB321/main/stream/6a25012909ffd978546c2ed1.json"
                      }
                    },
                    {
                      "id": "6a25012909ffd978546c2ed1_1",
                      "name": "Chuối To - HD2",
                      "remote_data": {
                        "url": "https://raw.githubusercontent.com/nghehoang007-wq/HFB321/main/stream/6a25012909ffd978546c2ed1.json"
                      }
                    },
                    {
                      "id": "6a25012909ffd978546c2ed1_2",
                      "name": "Chuối To - FHD1",
                      "remote_data": {
                        "url": "https://raw.githubusercontent.com/nghehoang007-wq/HFB321/main/stream/6a25012909ffd978546c2ed1.json"
                      }
                    },
                    {
                      "id": "6a25012909ffd978546c2ed1_3",
                      "name": "Chuối To - FHD2",
                      "remote_data": {
                        "url": "https://raw.githubusercontent.com/nghehoang007-wq/HFB321/main/stream/6a25012909ffd978546c2ed1.json"
                      }
                    }
                  ]
                }
              ]
            }
          ]
        },
        {
          "id": "6a24180809ffd97854508af3",
          "name": "Australia U19 vs Cambodia U19",
          "labels": [
            {
              "position": "bottom-center",
              "text": "20h00",
              "color": "#FF0000",
              "text_color": "#FFFFFF"
            },
            {
              "position": "top-left",
              "text": "Australia U19",
              "color": "#80000000",
              "text_color": "#FFFFFF"
            },
            {
              "position": "top-right",
              "text": "Cambodia U19",
              "color": "#80000000",
              "text_color": "#FFFFFF"
            }
          ],
          "image": {
            "url": "https://raw.githubusercontent.com/nghehoang007-wq/HFB321/main/thumbs/6a24180809ffd97854508af3.png",
            "height": 360,
            "width": 640,
            "display": "cover"
          },
          "type": "single",
          "display": "thumbnail-only",
          "sources": [
            {
              "id": "src-6a24180809ffd97854508af3",
              "name": "Chuối Chiên",
              "contents": [
                {
                  "id": "c-6a24180809ffd97854508af3",
                  "name": "Australia U19 vs Cambodia U19",
                  "streams": [
                    {
                      "id": "6a24180809ffd97854508af3_0",
                      "name": "Chuối Xuyên Không - HD1",
                      "remote_data": {
                        "url": "https://raw.githubusercontent.com/nghehoang007-wq/HFB321/main/stream/6a24180809ffd97854508af3.json"
                      }
                    },
                    {
                      "id": "6a24180809ffd97854508af3_1",
                      "name": "Chuối Xuyên Không - HD2",
                      "remote_data": {
                        "url": "https://raw.githubusercontent.com/nghehoang007-wq/HFB321/main/stream/6a24180809ffd97854508af3.json"
                      }
                    },
                    {
                      "id": "6a24180809ffd97854508af3_2",
                      "name": "Chuối Xuyên Không - FHD1",
                      "remote_data": {
                        "url": "https://raw.githubusercontent.com/nghehoang007-wq/HFB321/main/stream/6a24180809ffd97854508af3.json"
                      }
                    },
                    {
                      "id": "6a24180809ffd97854508af3_3",
                      "name": "Chuối Xuyên Không - FHD2",
                      "remote_data": {
                        "url": "https://raw.githubusercontent.com/nghehoang007-wq/HFB321/main/stream/6a24180809ffd97854508af3.json"
                      }
                    }
                  ]
                }
              ]
            }
          ]
        },
        {
          "id": "6a245342966a612324c16411",
          "name": "Kyrgyzstan W vs Australia W",
          "labels": [
            {
              "position": "bottom-center",
              "text": "20h00",
              "color": "#FF0000",
              "text_color": "#FFFFFF"
            },
            {
              "position": "top-left",
              "text": "Kyrgyzstan W",
              "color": "#80000000",
              "text_color": "#FFFFFF"
            },
            {
              "position": "top-right",
              "text": "Australia W",
              "color": "#80000000",
              "text_color": "#FFFFFF"
            }
          ],
          "image": {
            "url": "https://raw.githubusercontent.com/nghehoang007-wq/HFB321/main/thumbs/6a245342966a612324c16411.png",
            "height": 360,
            "width": 640,
            "display": "cover"
          },
          "type": "single",
          "display": "thumbnail-only",
          "sources": [
            {
              "id": "src-6a245342966a612324c16411",
              "name": "Chuối Chiên",
              "contents": [
                {
                  "id": "c-6a245342966a612324c16411",
                  "name": "Kyrgyzstan W vs Australia W",
                  "streams": [
                    {
                      "id": "6a245342966a612324c16411_0",
                      "name": "Chuối Bơ - HD1",
                      "remote_data": {
                        "url": "https://raw.githubusercontent.com/nghehoang007-wq/HFB321/main/stream/6a245342966a612324c16411.json"
                      }
                    },
                    {
                      "id": "6a245342966a612324c16411_1",
                      "name": "Chuối Bơ - HD2",
                      "remote_data": {
                        "url": "https://raw.githubusercontent.com/nghehoang007-wq/HFB321/main/stream/6a245342966a612324c16411.json"
                      }
                    },
                    {
                      "id": "6a245342966a612324c16411_2",
                      "name": "Chuối Bơ - FHD1",
                      "remote_data": {
                        "url": "https://raw.githubusercontent.com/nghehoang007-wq/HFB321/main/stream/6a245342966a612324c16411.json"
                      }
                    },
                    {
                      "id": "6a245342966a612324c16411_3",
                      "name": "Chuối Bơ - FHD2",
                      "remote_data": {
                        "url": "https://raw.githubusercontent.com/nghehoang007-wq/HFB321/main/stream/6a245342966a612324c16411.json"
                      }
                    }
                  ]
                }
              ]
            }
          ]
        },
        {
          "id": "6a25012909ffd978546c2edb",
          "name": "Indonesia vs Mozambique",
          "labels": [
            {
              "position": "bottom-center",
              "text": "20h00",
              "color": "#FF0000",
              "text_color": "#FFFFFF"
            },
            {
              "position": "top-left",
              "text": "Indonesia",
              "color": "#80000000",
              "text_color": "#FFFFFF"
            },
            {
              "position": "top-right",
              "text": "Mozambique",
              "color": "#80000000",
              "text_color": "#FFFFFF"
            }
          ],
          "image": {
            "url": "https://raw.githubusercontent.com/nghehoang007-wq/HFB321/main/thumbs/6a25012909ffd978546c2edb.png",
            "height": 360,
            "width": 640,
            "display": "cover"
          },
          "type": "single",
          "display": "thumbnail-only",
          "sources": [
            {
              "id": "src-6a25012909ffd978546c2edb",
              "name": "Chuối Chiên",
              "contents": [
                {
                  "id": "c-6a25012909ffd978546c2edb",
                  "name": "Indonesia vs Mozambique",
                  "streams": [
                    {
                      "id": "6a25012909ffd978546c2edb_0",
                      "name": "Cậu Cả - HD1",
                      "remote_data": {
                        "url": "https://raw.githubusercontent.com/nghehoang007-wq/HFB321/main/stream/6a25012909ffd978546c2edb.json"
                      }
                    },
                    {
                      "id": "6a25012909ffd978546c2edb_1",
                      "name": "Cậu Cả - HD2",
                      "remote_data": {
                        "url": "https://raw.githubusercontent.com/nghehoang007-wq/HFB321/main/stream/6a25012909ffd978546c2edb.json"
                      }
                    },
                    {
                      "id": "6a25012909ffd978546c2edb_2",
                      "name": "Cậu Cả - FHD1",
                      "remote_data": {
                        "url": "https://raw.githubusercontent.com/nghehoang007-wq/HFB321/main/stream/6a25012909ffd978546c2edb.json"
                      }
                    },
                    {
                      "id": "6a25012909ffd978546c2edb_3",
                      "name": "Cậu Cả - FHD2",
                      "remote_data": {
                        "url": "https://raw.githubusercontent.com/nghehoang007-wq/HFB321/main/stream/6a25012909ffd978546c2edb.json"
                      }
                    }
                  ]
                }
              ]
            }
          ]
        },
        {
          "id": "6a25012909ffd978546c2ecc",
          "name": "Armenia vs Moldova",
          "labels": [
            {
              "position": "bottom-center",
              "text": "22h00",
              "color": "#FF0000",
              "text_color": "#FFFFFF"
            },
            {
              "position": "top-left",
              "text": "Armenia",
              "color": "#80000000",
              "text_color": "#FFFFFF"
            },
            {
              "position": "top-right",
              "text": "Moldova",
              "color": "#80000000",
              "text_color": "#FFFFFF"
            }
          ],
          "image": {
            "url": "https://raw.githubusercontent.com/nghehoang007-wq/HFB321/main/thumbs/6a25012909ffd978546c2ecc.png",
            "height": 360,
            "width": 640,
            "display": "cover"
          },
          "type": "single",
          "display": "thumbnail-only",
          "sources": [
            {
              "id": "src-6a25012909ffd978546c2ecc",
              "name": "Chuối Chiên",
              "contents": [
                {
                  "id": "c-6a25012909ffd978546c2ecc",
                  "name": "Armenia vs Moldova",
                  "streams": [
                    {
                      "id": "6a25012909ffd978546c2ecc_0",
                      "name": "Chuối To - HD1",
                      "remote_data": {
                        "url": "https://raw.githubusercontent.com/nghehoang007-wq/HFB321/main/stream/6a25012909ffd978546c2ecc.json"
                      }
                    },
                    {
                      "id": "6a25012909ffd978546c2ecc_1",
                      "name": "Chuối To - HD2",
                      "remote_data": {
                        "url": "https://raw.githubusercontent.com/nghehoang007-wq/HFB321/main/stream/6a25012909ffd978546c2ecc.json"
                      }
                    },
                    {
                      "id": "6a25012909ffd978546c2ecc_2",
                      "name": "Chuối To - FHD1",
                      "remote_data": {
                        "url": "https://raw.githubusercontent.com/nghehoang007-wq/HFB321/main/stream/6a25012909ffd978546c2ecc.json"
                      }
                    },
                    {
                      "id": "6a25012909ffd978546c2ecc_3",
                      "name": "Chuối To - FHD2",
                      "remote_data": {
                        "url": "https://raw.githubusercontent.com/nghehoang007-wq/HFB321/main/stream/6a25012909ffd978546c2ecc.json"
                      }
                    }
                  ]
                }
              ]
            }
          ]
        },
        {
          "id": "6a25012909ffd978546c2edf",
          "name": "Tajikistan vs India",
          "labels": [
            {
              "position": "bottom-center",
              "text": "22h00",
              "color": "#FF0000",
              "text_color": "#FFFFFF"
            },
            {
              "position": "top-left",
              "text": "Tajikistan",
              "color": "#80000000",
              "text_color": "#FFFFFF"
            },
            {
              "position": "top-right",
              "text": "India",
              "color": "#80000000",
              "text_color": "#FFFFFF"
            }
          ],
          "image": {
            "url": "https://raw.githubusercontent.com/nghehoang007-wq/HFB321/main/thumbs/6a25012909ffd978546c2edf.png",
            "height": 360,
            "width": 640,
            "display": "cover"
          },
          "type": "single",
          "display": "thumbnail-only",
          "sources": [
            {
              "id": "src-6a25012909ffd978546c2edf",
              "name": "Chuối Chiên",
              "contents": [
                {
                  "id": "c-6a25012909ffd978546c2edf",
                  "name": "Tajikistan vs India",
                  "streams": [
                    {
                      "id": "6a25012909ffd978546c2edf_0",
                      "name": "Chuối Chao - HD1",
                      "remote_data": {
                        "url": "https://raw.githubusercontent.com/nghehoang007-wq/HFB321/main/stream/6a25012909ffd978546c2edf.json"
                      }
                    },
                    {
                      "id": "6a25012909ffd978546c2edf_1",
                      "name": "Chuối Chao - HD2",
                      "remote_data": {
                        "url": "https://raw.githubusercontent.com/nghehoang007-wq/HFB321/main/stream/6a25012909ffd978546c2edf.json"
                      }
                    },
                    {
                      "id": "6a25012909ffd978546c2edf_2",
                      "name": "Chuối Chao - FHD1",
                      "remote_data": {
                        "url": "https://raw.githubusercontent.com/nghehoang007-wq/HFB321/main/stream/6a25012909ffd978546c2edf.json"
                      }
                    },
                    {
                      "id": "6a25012909ffd978546c2edf_3",
                      "name": "Chuối Chao - FHD2",
                      "remote_data": {
                        "url": "https://raw.githubusercontent.com/nghehoang007-wq/HFB321/main/stream/6a25012909ffd978546c2edf.json"
                      }
                    }
                  ]
                }
              ]
            }
          ]
        },
        {
          "id": "6a25012909ffd978546c2ec3",
          "name": "Sweden W vs Italy W",
          "labels": [
            {
              "position": "bottom-center",
              "text": "00h00",
              "color": "#FF0000",
              "text_color": "#FFFFFF"
            },
            {
              "position": "top-left",
              "text": "Sweden W",
              "color": "#80000000",
              "text_color": "#FFFFFF"
            },
            {
              "position": "top-right",
              "text": "Italy W",
              "color": "#80000000",
              "text_color": "#FFFFFF"
            }
          ],
          "image": {
            "url": "https://raw.githubusercontent.com/nghehoang007-wq/HFB321/main/thumbs/6a25012909ffd978546c2ec3.png",
            "height": 360,
            "width": 640,
            "display": "cover"
          },
          "type": "single",
          "display": "thumbnail-only",
          "sources": [
            {
              "id": "src-6a25012909ffd978546c2ec3",
              "name": "Chuối Chiên",
              "contents": [
                {
                  "id": "c-6a25012909ffd978546c2ec3",
                  "name": "Sweden W vs Italy W",
                  "streams": [
                    {
                      "id": "6a25012909ffd978546c2ec3_0",
                      "name": "Chuối Xuyên Không - HD1",
                      "remote_data": {
                        "url": "https://raw.githubusercontent.com/nghehoang007-wq/HFB321/main/stream/6a25012909ffd978546c2ec3.json"
                      }
                    },
                    {
                      "id": "6a25012909ffd978546c2ec3_1",
                      "name": "Chuối Xuyên Không - HD2",
                      "remote_data": {
                        "url": "https://raw.githubusercontent.com/nghehoang007-wq/HFB321/main/stream/6a25012909ffd978546c2ec3.json"
                      }
                    },
                    {
                      "id": "6a25012909ffd978546c2ec3_2",
                      "name": "Chuối Xuyên Không - FHD1",
                      "remote_data": {
                        "url": "https://raw.githubusercontent.com/nghehoang007-wq/HFB321/main/stream/6a25012909ffd978546c2ec3.json"
                      }
                    },
                    {
                      "id": "6a25012909ffd978546c2ec3_3",
                      "name": "Chuối Xuyên Không - FHD2",
                      "remote_data": {
                        "url": "https://raw.githubusercontent.com/nghehoang007-wq/HFB321/main/stream/6a25012909ffd978546c2ec3.json"
                      }
                    }
                  ]
                }
              ]
            }
          ]
        },
        {
          "id": "6a25012909ffd978546c2ecb",
          "name": "Hungary vs Kazakhstan",
          "labels": [
            {
              "position": "bottom-center",
              "text": "00h00",
              "color": "#FF0000",
              "text_color": "#FFFFFF"
            },
            {
              "position": "top-left",
              "text": "Hungary",
              "color": "#80000000",
              "text_color": "#FFFFFF"
            },
            {
              "position": "top-right",
              "text": "Kazakhstan",
              "color": "#80000000",
              "text_color": "#FFFFFF"
            }
          ],
          "image": {
            "url": "https://raw.githubusercontent.com/nghehoang007-wq/HFB321/main/thumbs/6a25012909ffd978546c2ecb.png",
            "height": 360,
            "width": 640,
            "display": "cover"
          },
          "type": "single",
          "display": "thumbnail-only",
          "sources": [
            {
              "id": "src-6a25012909ffd978546c2ecb",
              "name": "Chuối Chiên",
              "contents": [
                {
                  "id": "c-6a25012909ffd978546c2ecb",
                  "name": "Hungary vs Kazakhstan",
                  "streams": [
                    {
                      "id": "6a25012909ffd978546c2ecb_0",
                      "name": "Chuối Nhỏ - HD1",
                      "remote_data": {
                        "url": "https://raw.githubusercontent.com/nghehoang007-wq/HFB321/main/stream/6a25012909ffd978546c2ecb.json"
                      }
                    },
                    {
                      "id": "6a25012909ffd978546c2ecb_1",
                      "name": "Chuối Nhỏ - HD2",
                      "remote_data": {
                        "url": "https://raw.githubusercontent.com/nghehoang007-wq/HFB321/main/stream/6a25012909ffd978546c2ecb.json"
                      }
                    },
                    {
                      "id": "6a25012909ffd978546c2ecb_2",
                      "name": "Chuối Nhỏ - FHD1",
                      "remote_data": {
                        "url": "https://raw.githubusercontent.com/nghehoang007-wq/HFB321/main/stream/6a25012909ffd978546c2ecb.json"
                      }
                    },
                    {
                      "id": "6a25012909ffd978546c2ecb_3",
                      "name": "Chuối Nhỏ - FHD2",
                      "remote_data": {
                        "url": "https://raw.githubusercontent.com/nghehoang007-wq/HFB321/main/stream/6a25012909ffd978546c2ecb.json"
                      }
                    }
                  ]
                }
              ]
            }
          ]
        },
        {
          "id": "6a26ef2c09ffd97854a39ce7",
          "name": "Russia vs Trinidad and Tobago",
          "labels": [
            {
              "position": "bottom-center",
              "text": "00h00",
              "color": "#FF0000",
              "text_color": "#FFFFFF"
            },
            {
              "position": "top-left",
              "text": "Russia",
              "color": "#80000000",
              "text_color": "#FFFFFF"
            },
            {
              "position": "top-right",
              "text": "Trinidad and..",
              "color": "#80000000",
              "text_color": "#FFFFFF"
            }
          ],
          "image": {
            "url": "https://raw.githubusercontent.com/nghehoang007-wq/HFB321/main/thumbs/6a26ef2c09ffd97854a39ce7.png",
            "height": 360,
            "width": 640,
            "display": "cover"
          },
          "type": "single",
          "display": "thumbnail-only",
          "sources": [
            {
              "id": "src-6a26ef2c09ffd97854a39ce7",
              "name": "Chuối Chiên",
              "contents": [
                {
                  "id": "c-6a26ef2c09ffd97854a39ce7",
                  "name": "Russia vs Trinidad and Tobago",
                  "streams": [
                    {
                      "id": "6a26ef2c09ffd97854a39ce7_0",
                      "name": "Chuối Tím - HD1",
                      "remote_data": {
                        "url": "https://raw.githubusercontent.com/nghehoang007-wq/HFB321/main/stream/6a26ef2c09ffd97854a39ce7.json"
                      }
                    },
                    {
                      "id": "6a26ef2c09ffd97854a39ce7_1",
                      "name": "Chuối Tím - HD2",
                      "remote_data": {
                        "url": "https://raw.githubusercontent.com/nghehoang007-wq/HFB321/main/stream/6a26ef2c09ffd97854a39ce7.json"
                      }
                    },
                    {
                      "id": "6a26ef2c09ffd97854a39ce7_2",
                      "name": "Chuối Tím - FHD1",
                      "remote_data": {
                        "url": "https://raw.githubusercontent.com/nghehoang007-wq/HFB321/main/stream/6a26ef2c09ffd97854a39ce7.json"
                      }
                    },
                    {
                      "id": "6a26ef2c09ffd97854a39ce7_3",
                      "name": "Chuối Tím - FHD2",
                      "remote_data": {
                        "url": "https://raw.githubusercontent.com/nghehoang007-wq/HFB321/main/stream/6a26ef2c09ffd97854a39ce7.json"
                      }
                    }
                  ]
                }
              ]
            }
          ]
        },
        {
          "id": "6a26ef2c09ffd97854a39ce8",
          "name": "Azerbaijan vs San Marino",
          "labels": [
            {
              "position": "bottom-center",
              "text": "01h00",
              "color": "#FF0000",
              "text_color": "#FFFFFF"
            },
            {
              "position": "top-left",
              "text": "Azerbaijan",
              "color": "#80000000",
              "text_color": "#FFFFFF"
            },
            {
              "position": "top-right",
              "text": "San Marino",
              "color": "#80000000",
              "text_color": "#FFFFFF"
            }
          ],
          "image": {
            "url": "https://raw.githubusercontent.com/nghehoang007-wq/HFB321/main/thumbs/6a26ef2c09ffd97854a39ce8.png",
            "height": 360,
            "width": 640,
            "display": "cover"
          },
          "type": "single",
          "display": "thumbnail-only",
          "sources": [
            {
              "id": "src-6a26ef2c09ffd97854a39ce8",
              "name": "Chuối Chiên",
              "contents": [
                {
                  "id": "c-6a26ef2c09ffd97854a39ce8",
                  "name": "Azerbaijan vs San Marino",
                  "streams": [
                    {
                      "id": "6a26ef2c09ffd97854a39ce8_0",
                      "name": "Cậu Cả - HD1",
                      "remote_data": {
                        "url": "https://raw.githubusercontent.com/nghehoang007-wq/HFB321/main/stream/6a26ef2c09ffd97854a39ce8.json"
                      }
                    },
                    {
                      "id": "6a26ef2c09ffd97854a39ce8_1",
                      "name": "Cậu Cả - HD2",
                      "remote_data": {
                        "url": "https://raw.githubusercontent.com/nghehoang007-wq/HFB321/main/stream/6a26ef2c09ffd97854a39ce8.json"
                      }
                    },
                    {
                      "id": "6a26ef2c09ffd97854a39ce8_2",
                      "name": "Cậu Cả - FHD1",
                      "remote_data": {
                        "url": "https://raw.githubusercontent.com/nghehoang007-wq/HFB321/main/stream/6a26ef2c09ffd97854a39ce8.json"
                      }
                    },
                    {
                      "id": "6a26ef2c09ffd97854a39ce8_3",
                      "name": "Cậu Cả - FHD2",
                      "remote_data": {
                        "url": "https://raw.githubusercontent.com/nghehoang007-wq/HFB321/main/stream/6a26ef2c09ffd97854a39ce8.json"
                      }
                    }
                  ]
                }
              ]
            }
          ]
        },
        {
          "id": "6a25012909ffd978546c2ec5",
          "name": "Netherlands W vs Poland W",
          "labels": [
            {
              "position": "bottom-center",
              "text": "02h00",
              "color": "#FF0000",
              "text_color": "#FFFFFF"
            },
            {
              "position": "top-left",
              "text": "Netherlands W",
              "color": "#80000000",
              "text_color": "#FFFFFF"
            },
            {
              "position": "top-right",
              "text": "Poland W",
              "color": "#80000000",
              "text_color": "#FFFFFF"
            }
          ],
          "image": {
            "url": "https://raw.githubusercontent.com/nghehoang007-wq/HFB321/main/thumbs/6a25012909ffd978546c2ec5.png",
            "height": 360,
            "width": 640,
            "display": "cover"
          },
          "type": "single",
          "display": "thumbnail-only",
          "sources": [
            {
              "id": "src-6a25012909ffd978546c2ec5",
              "name": "Chuối Chiên",
              "contents": [
                {
                  "id": "c-6a25012909ffd978546c2ec5",
                  "name": "Netherlands W vs Poland W",
                  "streams": [
                    {
                      "id": "6a25012909ffd978546c2ec5_0",
                      "name": "Chuối Bơ - HD1",
                      "remote_data": {
                        "url": "https://raw.githubusercontent.com/nghehoang007-wq/HFB321/main/stream/6a25012909ffd978546c2ec5.json"
                      }
                    },
                    {
                      "id": "6a25012909ffd978546c2ec5_1",
                      "name": "Chuối Bơ - HD2",
                      "remote_data": {
                        "url": "https://raw.githubusercontent.com/nghehoang007-wq/HFB321/main/stream/6a25012909ffd978546c2ec5.json"
                      }
                    },
                    {
                      "id": "6a25012909ffd978546c2ec5_2",
                      "name": "Chuối Bơ - FHD1",
                      "remote_data": {
                        "url": "https://raw.githubusercontent.com/nghehoang007-wq/HFB321/main/stream/6a25012909ffd978546c2ec5.json"
                      }
                    },
                    {
                      "id": "6a25012909ffd978546c2ec5_3",
                      "name": "Chuối Bơ - FHD2",
                      "remote_data": {
                        "url": "https://raw.githubusercontent.com/nghehoang007-wq/HFB321/main/stream/6a25012909ffd978546c2ec5.json"
                      }
                    }
                  ]
                }
              ]
            }
          ]
        },
        {
          "id": "6a26f23909ffd97854a3ec07",
          "name": "England W vs Ukraine W",
          "labels": [
            {
              "position": "bottom-center",
              "text": "02h00",
              "color": "#FF0000",
              "text_color": "#FFFFFF"
            },
            {
              "position": "top-left",
              "text": "England W",
              "color": "#80000000",
              "text_color": "#FFFFFF"
            },
            {
              "position": "top-right",
              "text": "Ukraine W",
              "color": "#80000000",
              "text_color": "#FFFFFF"
            }
          ],
          "image": {
            "url": "https://raw.githubusercontent.com/nghehoang007-wq/HFB321/main/thumbs/6a26f23909ffd97854a3ec07.png",
            "height": 360,
            "width": 640,
            "display": "cover"
          },
          "type": "single",
          "display": "thumbnail-only",
          "sources": [
            {
              "id": "src-6a26f23909ffd97854a3ec07",
              "name": "Chuối Chiên",
              "contents": [
                {
                  "id": "c-6a26f23909ffd97854a3ec07",
                  "name": "England W vs Ukraine W",
                  "streams": [
                    {
                      "id": "6a26f23909ffd97854a3ec07_0",
                      "name": "Chuối Tây - HD1",
                      "remote_data": {
                        "url": "https://raw.githubusercontent.com/nghehoang007-wq/HFB321/main/stream/6a26f23909ffd97854a3ec07.json"
                      }
                    },
                    {
                      "id": "6a26f23909ffd97854a3ec07_1",
                      "name": "Chuối Tây - HD2",
                      "remote_data": {
                        "url": "https://raw.githubusercontent.com/nghehoang007-wq/HFB321/main/stream/6a26f23909ffd97854a3ec07.json"
                      }
                    },
                    {
                      "id": "6a26f23909ffd97854a3ec07_2",
                      "name": "Chuối Tây - FHD1",
                      "remote_data": {
                        "url": "https://raw.githubusercontent.com/nghehoang007-wq/HFB321/main/stream/6a26f23909ffd97854a3ec07.json"
                      }
                    },
                    {
                      "id": "6a26f23909ffd97854a3ec07_3",
                      "name": "Chuối Tây - FHD2",
                      "remote_data": {
                        "url": "https://raw.githubusercontent.com/nghehoang007-wq/HFB321/main/stream/6a26f23909ffd97854a3ec07.json"
                      }
                    }
                  ]
                }
              ]
            }
          ]
        },
        {
          "id": "6a25012909ffd978546c2ed4",
          "name": "Saudi Arabia vs Senegal",
          "labels": [
            {
              "position": "bottom-center",
              "text": "06h00",
              "color": "#FF0000",
              "text_color": "#FFFFFF"
            },
            {
              "position": "top-left",
              "text": "Saudi Arabia",
              "color": "#80000000",
              "text_color": "#FFFFFF"
            },
            {
              "position": "top-right",
              "text": "Senegal",
              "color": "#80000000",
              "text_color": "#FFFFFF"
            }
          ],
          "image": {
            "url": "https://raw.githubusercontent.com/nghehoang007-wq/HFB321/main/thumbs/6a25012909ffd978546c2ed4.png",
            "height": 360,
            "width": 640,
            "display": "cover"
          },
          "type": "single",
          "display": "thumbnail-only",
          "sources": [
            {
              "id": "src-6a25012909ffd978546c2ed4",
              "name": "Chuối Chiên",
              "contents": [
                {
                  "id": "c-6a25012909ffd978546c2ed4",
                  "name": "Saudi Arabia vs Senegal",
                  "streams": [
                    {
                      "id": "6a25012909ffd978546c2ed4_0",
                      "name": "Chuối Tiêu - HD1",
                      "remote_data": {
                        "url": "https://raw.githubusercontent.com/nghehoang007-wq/HFB321/main/stream/6a25012909ffd978546c2ed4.json"
                      }
                    },
                    {
                      "id": "6a25012909ffd978546c2ed4_1",
                      "name": "Chuối Tiêu - HD2",
                      "remote_data": {
                        "url": "https://raw.githubusercontent.com/nghehoang007-wq/HFB321/main/stream/6a25012909ffd978546c2ed4.json"
                      }
                    },
                    {
                      "id": "6a25012909ffd978546c2ed4_2",
                      "name": "Chuối Tiêu - FHD1",
                      "remote_data": {
                        "url": "https://raw.githubusercontent.com/nghehoang007-wq/HFB321/main/stream/6a25012909ffd978546c2ed4.json"
                      }
                    },
                    {
                      "id": "6a25012909ffd978546c2ed4_3",
                      "name": "Chuối Tiêu - FHD2",
                      "remote_data": {
                        "url": "https://raw.githubusercontent.com/nghehoang007-wq/HFB321/main/stream/6a25012909ffd978546c2ed4.json"
                      }
                    }
                  ]
                }
              ]
            }
          ]
        },
        {
          "id": "6a26ef2c09ffd97854a39ce6",
          "name": "Argentina vs Iceland",
          "labels": [
            {
              "position": "bottom-center",
              "text": "08h00",
              "color": "#FF0000",
              "text_color": "#FFFFFF"
            },
            {
              "position": "top-left",
              "text": "Argentina",
              "color": "#80000000",
              "text_color": "#FFFFFF"
            },
            {
              "position": "top-right",
              "text": "Iceland",
              "color": "#80000000",
              "text_color": "#FFFFFF"
            }
          ],
          "image": {
            "url": "https://raw.githubusercontent.com/nghehoang007-wq/HFB321/main/thumbs/6a26ef2c09ffd97854a39ce6.png",
            "height": 360,
            "width": 640,
            "display": "cover"
          },
          "type": "single",
          "display": "thumbnail-only",
          "sources": [
            {
              "id": "src-6a26ef2c09ffd97854a39ce6",
              "name": "Chuối Chiên",
              "contents": [
                {
                  "id": "c-6a26ef2c09ffd97854a39ce6",
                  "name": "Argentina vs Iceland",
                  "streams": [
                    {
                      "id": "6a26ef2c09ffd97854a39ce6_0",
                      "name": "Trốc Tru - HD1",
                      "remote_data": {
                        "url": "https://raw.githubusercontent.com/nghehoang007-wq/HFB321/main/stream/6a26ef2c09ffd97854a39ce6.json"
                      }
                    },
                    {
                      "id": "6a26ef2c09ffd97854a39ce6_1",
                      "name": "Trốc Tru - HD2",
                      "remote_data": {
                        "url": "https://raw.githubusercontent.com/nghehoang007-wq/HFB321/main/stream/6a26ef2c09ffd97854a39ce6.json"
                      }
                    },
                    {
                      "id": "6a26ef2c09ffd97854a39ce6_2",
                      "name": "Trốc Tru - FHD1",
                      "remote_data": {
                        "url": "https://raw.githubusercontent.com/nghehoang007-wq/HFB321/main/stream/6a26ef2c09ffd97854a39ce6.json"
                      }
                    },
                    {
                      "id": "6a26ef2c09ffd97854a39ce6_3",
                      "name": "Trốc Tru - FHD2",
                      "remote_data": {
                        "url": "https://raw.githubusercontent.com/nghehoang007-wq/HFB321/main/stream/6a26ef2c09ffd97854a39ce6.json"
                      }
                    }
                  ]
                }
              ]
            }
          ]
        }
      ]
    }
  ],
  "notice": {
    "id": "notice",
    "link": "https://t.me",
    "icon": "https://raw.githubusercontent.com/nghehoang007-wq/HFB321/main/HFB/Thump/chuoichien.png",
    "closeable": true
  },
  "cache_time": 5,
  "option": {
    "save_history": true,
    "save_search_history": false,
    "save_wishlist": false
  }
}