{
  "id": "chuoichienhfb",
  "url": "https://hfbtv.vercel.app/chuoichientv.json",
  "name": "Chuối Chiên TV",
  "color": "#003A17",
  "description": "Cập nhật trực tiếp từ Chuối Chiên TV",
  "image": {
    "url": "https://raw.githubusercontent.com/nghehoang007-wq/HFB321/main/HFB/Thump/chuoichien.png"
  },
  "groups": [
    {
      "id": "live",
      "name": "🔴 TRỰC TIẾP CHUỐI CHIÊN",
      "display": "vertical",
      "grid_number": 2,
      "channels": [
        {
          "id": "6a537aea09ffd978548acb99",
          "name": "Marlin Coast vs Brunswick Juventus FC",
          "labels": [
            {
              "position": "bottom-center",
              "text": "16h30",
              "color": "#FF0000",
              "text_color": "#FFFFFF"
            },
            {
              "position": "top-left",
              "text": "Marlin Coast",
              "color": "#80000000",
              "text_color": "#FFFFFF"
            },
            {
              "position": "top-right",
              "text": "Brunswick Ju..",
              "color": "#80000000",
              "text_color": "#FFFFFF"
            }
          ],
          "image": {
            "url": "https://raw.githubusercontent.com/nghehoang007-wq/HFB321/main/thumbs/6a537aea09ffd978548acb99.png",
            "height": 360,
            "width": 640,
            "display": "cover"
          },
          "type": "single",
          "display": "thumbnail-only",
          "sources": [
            {
              "id": "src-6a537aea09ffd978548acb99",
              "name": "Chuối Chiên",
              "contents": [
                {
                  "id": "c-6a537aea09ffd978548acb99",
                  "name": "Marlin Coast vs Brunswick Juventus FC",
                  "streams": [
                    {
                      "id": "6a537aea09ffd978548acb99_0",
                      "name": "Chuối Tiêu - HD1",
                      "remote_data": {
                        "url": "https://raw.githubusercontent.com/nghehoang007-wq/HFB321/main/stream/6a537aea09ffd978548acb99.json"
                      }
                    },
                    {
                      "id": "6a537aea09ffd978548acb99_1",
                      "name": "Chuối Tiêu - HD2",
                      "remote_data": {
                        "url": "https://raw.githubusercontent.com/nghehoang007-wq/HFB321/main/stream/6a537aea09ffd978548acb99.json"
                      }
                    },
                    {
                      "id": "6a537aea09ffd978548acb99_2",
                      "name": "Chuối Tiêu - FHD1",
                      "remote_data": {
                        "url": "https://raw.githubusercontent.com/nghehoang007-wq/HFB321/main/stream/6a537aea09ffd978548acb99.json"
                      }
                    },
                    {
                      "id": "6a537aea09ffd978548acb99_3",
                      "name": "Chuối Tiêu - FHD2",
                      "remote_data": {
                        "url": "https://raw.githubusercontent.com/nghehoang007-wq/HFB321/main/stream/6a537aea09ffd978548acb99.json"
                      }
                    }
                  ]
                }
              ]
            }
          ]
        },
        {
          "id": "6a555b1909ffd97854bcde17",
          "name": "White City Woodville vs North Sunshine Eagles",
          "labels": [
            {
              "position": "bottom-center",
              "text": "17h00",
              "color": "#FF0000",
              "text_color": "#FFFFFF"
            },
            {
              "position": "top-left",
              "text": "White City W..",
              "color": "#80000000",
              "text_color": "#FFFFFF"
            },
            {
              "position": "top-right",
              "text": "North Sunshi..",
              "color": "#80000000",
              "text_color": "#FFFFFF"
            }
          ],
          "image": {
            "url": "https://raw.githubusercontent.com/nghehoang007-wq/HFB321/main/thumbs/6a555b1909ffd97854bcde17.png",
            "height": 360,
            "width": 640,
            "display": "cover"
          },
          "type": "single",
          "display": "thumbnail-only",
          "sources": [
            {
              "id": "src-6a555b1909ffd97854bcde17",
              "name": "Chuối Chiên",
              "contents": [
                {
                  "id": "c-6a555b1909ffd97854bcde17",
                  "name": "White City Woodville vs North Sunshine Eagles",
                  "streams": [
                    {
                      "id": "6a555b1909ffd97854bcde17_0",
                      "name": "Chuối Chao - HD1",
                      "remote_data": {
                        "url": "https://raw.githubusercontent.com/nghehoang007-wq/HFB321/main/stream/6a555b1909ffd97854bcde17.json"
                      }
                    },
                    {
                      "id": "6a555b1909ffd97854bcde17_1",
                      "name": "Chuối Chao - HD2",
                      "remote_data": {
                        "url": "https://raw.githubusercontent.com/nghehoang007-wq/HFB321/main/stream/6a555b1909ffd97854bcde17.json"
                      }
                    },
                    {
                      "id": "6a555b1909ffd97854bcde17_2",
                      "name": "Chuối Chao - FHD1",
                      "remote_data": {
                        "url": "https://raw.githubusercontent.com/nghehoang007-wq/HFB321/main/stream/6a555b1909ffd97854bcde17.json"
                      }
                    },
                    {
                      "id": "6a555b1909ffd97854bcde17_3",
                      "name": "Chuối Chao - FHD2",
                      "remote_data": {
                        "url": "https://raw.githubusercontent.com/nghehoang007-wq/HFB321/main/stream/6a555b1909ffd97854bcde17.json"
                      }
                    }
                  ]
                }
              ]
            }
          ]
        },
        {
          "id": "6a56a67409ffd97854dfe64f",
          "name": "Busan Transportation vs Suwon Bluewings",
          "labels": [
            {
              "position": "bottom-center",
              "text": "17h00",
              "color": "#FF0000",
              "text_color": "#FFFFFF"
            },
            {
              "position": "top-left",
              "text": "Busan Transp..",
              "color": "#80000000",
              "text_color": "#FFFFFF"
            },
            {
              "position": "top-right",
              "text": "Suwon Bluewi..",
              "color": "#80000000",
              "text_color": "#FFFFFF"
            }
          ],
          "image": {
            "url": "https://raw.githubusercontent.com/nghehoang007-wq/HFB321/main/thumbs/6a56a67409ffd97854dfe64f.png",
            "height": 360,
            "width": 640,
            "display": "cover"
          },
          "type": "single",
          "display": "thumbnail-only",
          "sources": [
            {
              "id": "src-6a56a67409ffd97854dfe64f",
              "name": "Chuối Chiên",
              "contents": [
                {
                  "id": "c-6a56a67409ffd97854dfe64f",
                  "name": "Busan Transportation vs Suwon Bluewings",
                  "streams": [
                    {
                      "id": "6a56a67409ffd97854dfe64f_0",
                      "name": "Chuối To - HD1",
                      "remote_data": {
                        "url": "https://raw.githubusercontent.com/nghehoang007-wq/HFB321/main/stream/6a56a67409ffd97854dfe64f.json"
                      }
                    },
                    {
                      "id": "6a56a67409ffd97854dfe64f_1",
                      "name": "Chuối To - HD2",
                      "remote_data": {
                        "url": "https://raw.githubusercontent.com/nghehoang007-wq/HFB321/main/stream/6a56a67409ffd97854dfe64f.json"
                      }
                    },
                    {
                      "id": "6a56a67409ffd97854dfe64f_2",
                      "name": "Chuối To - FHD1",
                      "remote_data": {
                        "url": "https://raw.githubusercontent.com/nghehoang007-wq/HFB321/main/stream/6a56a67409ffd97854dfe64f.json"
                      }
                    },
                    {
                      "id": "6a56a67409ffd97854dfe64f_3",
                      "name": "Chuối To - FHD2",
                      "remote_data": {
                        "url": "https://raw.githubusercontent.com/nghehoang007-wq/HFB321/main/stream/6a56a67409ffd97854dfe64f.json"
                      }
                    }
                  ]
                }
              ]
            }
          ]
        },
        {
          "id": "6a57574b09ffd97854f20d64",
          "name": "Ansan Greeners vs Jinju Citizen",
          "labels": [
            {
              "position": "bottom-center",
              "text": "17h00",
              "color": "#FF0000",
              "text_color": "#FFFFFF"
            },
            {
              "position": "top-left",
              "text": "Ansan Greene..",
              "color": "#80000000",
              "text_color": "#FFFFFF"
            },
            {
              "position": "top-right",
              "text": "Jinju Citizen",
              "color": "#80000000",
              "text_color": "#FFFFFF"
            }
          ],
          "image": {
            "url": "https://raw.githubusercontent.com/nghehoang007-wq/HFB321/main/thumbs/6a57574b09ffd97854f20d64.png",
            "height": 360,
            "width": 640,
            "display": "cover"
          },
          "type": "single",
          "display": "thumbnail-only",
          "sources": [
            {
              "id": "src-6a57574b09ffd97854f20d64",
              "name": "Chuối Chiên",
              "contents": [
                {
                  "id": "c-6a57574b09ffd97854f20d64",
                  "name": "Ansan Greeners vs Jinju Citizen",
                  "streams": [
                    {
                      "id": "6a57574b09ffd97854f20d64_0",
                      "name": "Chuối Nhỏ - HD1",
                      "remote_data": {
                        "url": "https://raw.githubusercontent.com/nghehoang007-wq/HFB321/main/stream/6a57574b09ffd97854f20d64.json"
                      }
                    },
                    {
                      "id": "6a57574b09ffd97854f20d64_1",
                      "name": "Chuối Nhỏ - HD2",
                      "remote_data": {
                        "url": "https://raw.githubusercontent.com/nghehoang007-wq/HFB321/main/stream/6a57574b09ffd97854f20d64.json"
                      }
                    },
                    {
                      "id": "6a57574b09ffd97854f20d64_2",
                      "name": "Chuối Nhỏ - FHD1",
                      "remote_data": {
                        "url": "https://raw.githubusercontent.com/nghehoang007-wq/HFB321/main/stream/6a57574b09ffd97854f20d64.json"
                      }
                    },
                    {
                      "id": "6a57574b09ffd97854f20d64_3",
                      "name": "Chuối Nhỏ - FHD2",
                      "remote_data": {
                        "url": "https://raw.githubusercontent.com/nghehoang007-wq/HFB321/main/stream/6a57574b09ffd97854f20d64.json"
                      }
                    }
                  ]
                }
              ]
            }
          ]
        },
        {
          "id": "6a56259c09ffd97854d12060",
          "name": "Japan vs Italy",
          "labels": [
            {
              "position": "bottom-center",
              "text": "17h20",
              "color": "#FF0000",
              "text_color": "#FFFFFF"
            },
            {
              "position": "top-left",
              "text": "Japan",
              "color": "#80000000",
              "text_color": "#FFFFFF"
            },
            {
              "position": "top-right",
              "text": "Italy",
              "color": "#80000000",
              "text_color": "#FFFFFF"
            }
          ],
          "image": {
            "url": "https://raw.githubusercontent.com/nghehoang007-wq/HFB321/main/thumbs/6a56259c09ffd97854d12060.png",
            "height": 360,
            "width": 640,
            "display": "cover"
          },
          "type": "single",
          "display": "thumbnail-only",
          "sources": [
            {
              "id": "src-6a56259c09ffd97854d12060",
              "name": "Chuối Chiên",
              "contents": [
                {
                  "id": "c-6a56259c09ffd97854d12060",
                  "name": "Japan vs Italy",
                  "streams": [
                    {
                      "id": "6a56259c09ffd97854d12060_0",
                      "name": "Chuối Bơ - HD1",
                      "remote_data": {
                        "url": "https://raw.githubusercontent.com/nghehoang007-wq/HFB321/main/stream/6a56259c09ffd97854d12060.json"
                      }
                    },
                    {
                      "id": "6a56259c09ffd97854d12060_1",
                      "name": "Chuối Bơ - HD2",
                      "remote_data": {
                        "url": "https://raw.githubusercontent.com/nghehoang007-wq/HFB321/main/stream/6a56259c09ffd97854d12060.json"
                      }
                    },
                    {
                      "id": "6a56259c09ffd97854d12060_2",
                      "name": "Chuối Bơ - FHD1",
                      "remote_data": {
                        "url": "https://raw.githubusercontent.com/nghehoang007-wq/HFB321/main/stream/6a56259c09ffd97854d12060.json"
                      }
                    },
                    {
                      "id": "6a56259c09ffd97854d12060_3",
                      "name": "Chuối Bơ - FHD2",
                      "remote_data": {
                        "url": "https://raw.githubusercontent.com/nghehoang007-wq/HFB321/main/stream/6a56259c09ffd97854d12060.json"
                      }
                    }
                  ]
                }
              ]
            }
          ]
        },
        {
          "id": "6a56259c09ffd97854d12061",
          "name": "Germany vs Slovenia",
          "labels": [
            {
              "position": "bottom-center",
              "text": "18h00",
              "color": "#FF0000",
              "text_color": "#FFFFFF"
            },
            {
              "position": "top-left",
              "text": "Germany",
              "color": "#80000000",
              "text_color": "#FFFFFF"
            },
            {
              "position": "top-right",
              "text": "Slovenia",
              "color": "#80000000",
              "text_color": "#FFFFFF"
            }
          ],
          "image": {
            "url": "https://raw.githubusercontent.com/nghehoang007-wq/HFB321/main/thumbs/6a56259c09ffd97854d12061.png",
            "height": 360,
            "width": 640,
            "display": "cover"
          },
          "type": "single",
          "display": "thumbnail-only",
          "sources": [
            {
              "id": "src-6a56259c09ffd97854d12061",
              "name": "Chuối Chiên",
              "contents": [
                {
                  "id": "c-6a56259c09ffd97854d12061",
                  "name": "Germany vs Slovenia",
                  "streams": [
                    {
                      "id": "6a56259c09ffd97854d12061_0",
                      "name": "Chuối Già - HD1",
                      "remote_data": {
                        "url": "https://raw.githubusercontent.com/nghehoang007-wq/HFB321/main/stream/6a56259c09ffd97854d12061.json"
                      }
                    },
                    {
                      "id": "6a56259c09ffd97854d12061_1",
                      "name": "Chuối Già - HD2",
                      "remote_data": {
                        "url": "https://raw.githubusercontent.com/nghehoang007-wq/HFB321/main/stream/6a56259c09ffd97854d12061.json"
                      }
                    },
                    {
                      "id": "6a56259c09ffd97854d12061_2",
                      "name": "Chuối Già - FHD1",
                      "remote_data": {
                        "url": "https://raw.githubusercontent.com/nghehoang007-wq/HFB321/main/stream/6a56259c09ffd97854d12061.json"
                      }
                    },
                    {
                      "id": "6a56259c09ffd97854d12061_3",
                      "name": "Chuối Già - FHD2",
                      "remote_data": {
                        "url": "https://raw.githubusercontent.com/nghehoang007-wq/HFB321/main/stream/6a56259c09ffd97854d12061.json"
                      }
                    }
                  ]
                }
              ]
            }
          ]
        },
        {
          "id": "6a537aea09ffd978548acb94",
          "name": "Malisheva vs Vllaznia Shkodër",
          "labels": [
            {
              "position": "bottom-center",
              "text": "21h30",
              "color": "#FF0000",
              "text_color": "#FFFFFF"
            },
            {
              "position": "top-left",
              "text": "Malisheva",
              "color": "#80000000",
              "text_color": "#FFFFFF"
            },
            {
              "position": "top-right",
              "text": "Vllaznia Shk..",
              "color": "#80000000",
              "text_color": "#FFFFFF"
            }
          ],
          "image": {
            "url": "https://raw.githubusercontent.com/nghehoang007-wq/HFB321/main/thumbs/6a537aea09ffd978548acb94.png",
            "height": 360,
            "width": 640,
            "display": "cover"
          },
          "type": "single",
          "display": "thumbnail-only",
          "sources": [
            {
              "id": "src-6a537aea09ffd978548acb94",
              "name": "Chuối Chiên",
              "contents": [
                {
                  "id": "c-6a537aea09ffd978548acb94",
                  "name": "Malisheva vs Vllaznia Shkodër",
                  "streams": [
                    {
                      "id": "6a537aea09ffd978548acb94_0",
                      "name": "A Ngao - HD1",
                      "remote_data": {
                        "url": "https://raw.githubusercontent.com/nghehoang007-wq/HFB321/main/stream/6a537aea09ffd978548acb94.json"
                      }
                    },
                    {
                      "id": "6a537aea09ffd978548acb94_1",
                      "name": "A Ngao - HD2",
                      "remote_data": {
                        "url": "https://raw.githubusercontent.com/nghehoang007-wq/HFB321/main/stream/6a537aea09ffd978548acb94.json"
                      }
                    },
                    {
                      "id": "6a537aea09ffd978548acb94_2",
                      "name": "A Ngao - FHD1",
                      "remote_data": {
                        "url": "https://raw.githubusercontent.com/nghehoang007-wq/HFB321/main/stream/6a537aea09ffd978548acb94.json"
                      }
                    },
                    {
                      "id": "6a537aea09ffd978548acb94_3",
                      "name": "A Ngao - FHD2",
                      "remote_data": {
                        "url": "https://raw.githubusercontent.com/nghehoang007-wq/HFB321/main/stream/6a537aea09ffd978548acb94.json"
                      }
                    }
                  ]
                }
              ]
            }
          ]
        },
        {
          "id": "6a56259c09ffd97854d12062",
          "name": "Ukraine vs Iran",
          "labels": [
            {
              "position": "bottom-center",
              "text": "21h30",
              "color": "#FF0000",
              "text_color": "#FFFFFF"
            },
            {
              "position": "top-left",
              "text": "Ukraine",
              "color": "#80000000",
              "text_color": "#FFFFFF"
            },
            {
              "position": "top-right",
              "text": "Iran",
              "color": "#80000000",
              "text_color": "#FFFFFF"
            }
          ],
          "image": {
            "url": "https://raw.githubusercontent.com/nghehoang007-wq/HFB321/main/thumbs/6a56259c09ffd97854d12062.png",
            "height": 360,
            "width": 640,
            "display": "cover"
          },
          "type": "single",
          "display": "thumbnail-only",
          "sources": [
            {
              "id": "src-6a56259c09ffd97854d12062",
              "name": "Chuối Chiên",
              "contents": [
                {
                  "id": "c-6a56259c09ffd97854d12062",
                  "name": "Ukraine vs Iran",
                  "streams": [
                    {
                      "id": "6a56259c09ffd97854d12062_0",
                      "name": "Chuối Tây - HD1",
                      "remote_data": {
                        "url": "https://raw.githubusercontent.com/nghehoang007-wq/HFB321/main/stream/6a56259c09ffd97854d12062.json"
                      }
                    },
                    {
                      "id": "6a56259c09ffd97854d12062_1",
                      "name": "Chuối Tây - HD2",
                      "remote_data": {
                        "url": "https://raw.githubusercontent.com/nghehoang007-wq/HFB321/main/stream/6a56259c09ffd97854d12062.json"
                      }
                    },
                    {
                      "id": "6a56259c09ffd97854d12062_2",
                      "name": "Chuối Tây - FHD1",
                      "remote_data": {
                        "url": "https://raw.githubusercontent.com/nghehoang007-wq/HFB321/main/stream/6a56259c09ffd97854d12062.json"
                      }
                    },
                    {
                      "id": "6a56259c09ffd97854d12062_3",
                      "name": "Chuối Tây - FHD2",
                      "remote_data": {
                        "url": "https://raw.githubusercontent.com/nghehoang007-wq/HFB321/main/stream/6a56259c09ffd97854d12062.json"
                      }
                    }
                  ]
                }
              ]
            }
          ]
        },
        {
          "id": "6a56a7d409ffd97854e00a59",
          "name": "JIPPO vs MP",
          "labels": [
            {
              "position": "bottom-center",
              "text": "22h30",
              "color": "#FF0000",
              "text_color": "#FFFFFF"
            },
            {
              "position": "top-left",
              "text": "JIPPO",
              "color": "#80000000",
              "text_color": "#FFFFFF"
            },
            {
              "position": "top-right",
              "text": "MP",
              "color": "#80000000",
              "text_color": "#FFFFFF"
            }
          ],
          "image": {
            "url": "https://raw.githubusercontent.com/nghehoang007-wq/HFB321/main/thumbs/6a56a7d409ffd97854e00a59.png",
            "height": 360,
            "width": 640,
            "display": "cover"
          },
          "type": "single",
          "display": "thumbnail-only",
          "sources": [
            {
              "id": "src-6a56a7d409ffd97854e00a59",
              "name": "Chuối Chiên",
              "contents": [
                {
                  "id": "c-6a56a7d409ffd97854e00a59",
                  "name": "JIPPO vs MP",
                  "streams": [
                    {
                      "id": "6a56a7d409ffd97854e00a59_0",
                      "name": "Trốc Tru - HD1",
                      "remote_data": {
                        "url": "https://raw.githubusercontent.com/nghehoang007-wq/HFB321/main/stream/6a56a7d409ffd97854e00a59.json"
                      }
                    },
                    {
                      "id": "6a56a7d409ffd97854e00a59_1",
                      "name": "Trốc Tru - HD2",
                      "remote_data": {
                        "url": "https://raw.githubusercontent.com/nghehoang007-wq/HFB321/main/stream/6a56a7d409ffd97854e00a59.json"
                      }
                    },
                    {
                      "id": "6a56a7d409ffd97854e00a59_2",
                      "name": "Trốc Tru - FHD1",
                      "remote_data": {
                        "url": "https://raw.githubusercontent.com/nghehoang007-wq/HFB321/main/stream/6a56a7d409ffd97854e00a59.json"
                      }
                    },
                    {
                      "id": "6a56a7d409ffd97854e00a59_3",
                      "name": "Trốc Tru - FHD2",
                      "remote_data": {
                        "url": "https://raw.githubusercontent.com/nghehoang007-wq/HFB321/main/stream/6a56a7d409ffd97854e00a59.json"
                      }
                    }
                  ]
                }
              ]
            }
          ]
        },
        {
          "id": "6a56259c09ffd97854d12063",
          "name": "Bulgaria vs Poland",
          "labels": [
            {
              "position": "bottom-center",
              "text": "00h00",
              "color": "#FF0000",
              "text_color": "#FFFFFF"
            },
            {
              "position": "top-left",
              "text": "Bulgaria",
              "color": "#80000000",
              "text_color": "#FFFFFF"
            },
            {
              "position": "top-right",
              "text": "Poland",
              "color": "#80000000",
              "text_color": "#FFFFFF"
            }
          ],
          "image": {
            "url": "https://raw.githubusercontent.com/nghehoang007-wq/HFB321/main/thumbs/6a56259c09ffd97854d12063.png",
            "height": 360,
            "width": 640,
            "display": "cover"
          },
          "type": "single",
          "display": "thumbnail-only",
          "sources": [
            {
              "id": "src-6a56259c09ffd97854d12063",
              "name": "Chuối Chiên",
              "contents": [
                {
                  "id": "c-6a56259c09ffd97854d12063",
                  "name": "Bulgaria vs Poland",
                  "streams": [
                    {
                      "id": "6a56259c09ffd97854d12063_0",
                      "name": "Chuối Bơ - HD1",
                      "remote_data": {
                        "url": "https://raw.githubusercontent.com/nghehoang007-wq/HFB321/main/stream/6a56259c09ffd97854d12063.json"
                      }
                    },
                    {
                      "id": "6a56259c09ffd97854d12063_1",
                      "name": "Chuối Bơ - HD2",
                      "remote_data": {
                        "url": "https://raw.githubusercontent.com/nghehoang007-wq/HFB321/main/stream/6a56259c09ffd97854d12063.json"
                      }
                    },
                    {
                      "id": "6a56259c09ffd97854d12063_2",
                      "name": "Chuối Bơ - FHD1",
                      "remote_data": {
                        "url": "https://raw.githubusercontent.com/nghehoang007-wq/HFB321/main/stream/6a56259c09ffd97854d12063.json"
                      }
                    },
                    {
                      "id": "6a56259c09ffd97854d12063_3",
                      "name": "Chuối Bơ - FHD2",
                      "remote_data": {
                        "url": "https://raw.githubusercontent.com/nghehoang007-wq/HFB321/main/stream/6a56259c09ffd97854d12063.json"
                      }
                    }
                  ]
                }
              ]
            }
          ]
        },
        {
          "id": "6a54648b09ffd97854a3e606",
          "name": "Universitatea Craiova vs MKK-Dnepr",
          "labels": [
            {
              "position": "bottom-center",
              "text": "00h30",
              "color": "#FF0000",
              "text_color": "#FFFFFF"
            },
            {
              "position": "top-left",
              "text": "Universitate..",
              "color": "#80000000",
              "text_color": "#FFFFFF"
            },
            {
              "position": "top-right",
              "text": "MKK-Dnepr",
              "color": "#80000000",
              "text_color": "#FFFFFF"
            }
          ],
          "image": {
            "url": "https://raw.githubusercontent.com/nghehoang007-wq/HFB321/main/thumbs/6a54648b09ffd97854a3e606.png",
            "height": 360,
            "width": 640,
            "display": "cover"
          },
          "type": "single",
          "display": "thumbnail-only",
          "sources": [
            {
              "id": "src-6a54648b09ffd97854a3e606",
              "name": "Chuối Chiên",
              "contents": [
                {
                  "id": "c-6a54648b09ffd97854a3e606",
                  "name": "Universitatea Craiova vs MKK-Dnepr",
                  "streams": [
                    {
                      "id": "6a54648b09ffd97854a3e606_0",
                      "name": "Chuối Tiêu - HD1",
                      "remote_data": {
                        "url": "https://raw.githubusercontent.com/nghehoang007-wq/HFB321/main/stream/6a54648b09ffd97854a3e606.json"
                      }
                    },
                    {
                      "id": "6a54648b09ffd97854a3e606_1",
                      "name": "Chuối Tiêu - HD2",
                      "remote_data": {
                        "url": "https://raw.githubusercontent.com/nghehoang007-wq/HFB321/main/stream/6a54648b09ffd97854a3e606.json"
                      }
                    },
                    {
                      "id": "6a54648b09ffd97854a3e606_2",
                      "name": "Chuối Tiêu - FHD1",
                      "remote_data": {
                        "url": "https://raw.githubusercontent.com/nghehoang007-wq/HFB321/main/stream/6a54648b09ffd97854a3e606.json"
                      }
                    },
                    {
                      "id": "6a54648b09ffd97854a3e606_3",
                      "name": "Chuối Tiêu - FHD2",
                      "remote_data": {
                        "url": "https://raw.githubusercontent.com/nghehoang007-wq/HFB321/main/stream/6a54648b09ffd97854a3e606.json"
                      }
                    }
                  ]
                }
              ]
            }
          ]
        },
        {
          "id": "6a56a74209ffd97854dffb60",
          "name": "England vs Argentina",
          "labels": [
            {
              "position": "bottom-center",
              "text": "02h00",
              "color": "#FF0000",
              "text_color": "#FFFFFF"
            },
            {
              "position": "top-left",
              "text": "England",
              "color": "#80000000",
              "text_color": "#FFFFFF"
            },
            {
              "position": "top-right",
              "text": "Argentina",
              "color": "#80000000",
              "text_color": "#FFFFFF"
            }
          ],
          "image": {
            "url": "https://raw.githubusercontent.com/nghehoang007-wq/HFB321/main/thumbs/6a56a74209ffd97854dffb60.png",
            "height": 360,
            "width": 640,
            "display": "cover"
          },
          "type": "single",
          "display": "thumbnail-only",
          "sources": [
            {
              "id": "src-6a56a74209ffd97854dffb60",
              "name": "Chuối Chiên",
              "contents": [
                {
                  "id": "c-6a56a74209ffd97854dffb60",
                  "name": "England vs Argentina",
                  "streams": [
                    {
                      "id": "6a56a74209ffd97854dffb60_0",
                      "name": "Chuối Nhỏ - HD1",
                      "remote_data": {
                        "url": "https://raw.githubusercontent.com/nghehoang007-wq/HFB321/main/stream/6a56a74209ffd97854dffb60.json"
                      }
                    },
                    {
                      "id": "6a56a74209ffd97854dffb60_1",
                      "name": "Chuối Nhỏ - HD2",
                      "remote_data": {
                        "url": "https://raw.githubusercontent.com/nghehoang007-wq/HFB321/main/stream/6a56a74209ffd97854dffb60.json"
                      }
                    },
                    {
                      "id": "6a56a74209ffd97854dffb60_2",
                      "name": "Chuối Nhỏ - FHD1",
                      "remote_data": {
                        "url": "https://raw.githubusercontent.com/nghehoang007-wq/HFB321/main/stream/6a56a74209ffd97854dffb60.json"
                      }
                    },
                    {
                      "id": "6a56a74209ffd97854dffb60_3",
                      "name": "Chuối Nhỏ - FHD2",
                      "remote_data": {
                        "url": "https://raw.githubusercontent.com/nghehoang007-wq/HFB321/main/stream/6a56a74209ffd97854dffb60.json"
                      }
                    }
                  ]
                }
              ]
            }
          ]
        },
        {
          "id": "6a56259c09ffd97854d12065",
          "name": "France vs Brazil",
          "labels": [
            {
              "position": "bottom-center",
              "text": "04h00",
              "color": "#FF0000",
              "text_color": "#FFFFFF"
            },
            {
              "position": "top-left",
              "text": "France",
              "color": "#80000000",
              "text_color": "#FFFFFF"
            },
            {
              "position": "top-right",
              "text": "Brazil",
              "color": "#80000000",
              "text_color": "#FFFFFF"
            }
          ],
          "image": {
            "url": "https://raw.githubusercontent.com/nghehoang007-wq/HFB321/main/thumbs/6a56259c09ffd97854d12065.png",
            "height": 360,
            "width": 640,
            "display": "cover"
          },
          "type": "single",
          "display": "thumbnail-only",
          "sources": [
            {
              "id": "src-6a56259c09ffd97854d12065",
              "name": "Chuối Chiên",
              "contents": [
                {
                  "id": "c-6a56259c09ffd97854d12065",
                  "name": "France vs Brazil",
                  "streams": [
                    {
                      "id": "6a56259c09ffd97854d12065_0",
                      "name": "Chuối Già - HD1",
                      "remote_data": {
                        "url": "https://raw.githubusercontent.com/nghehoang007-wq/HFB321/main/stream/6a56259c09ffd97854d12065.json"
                      }
                    },
                    {
                      "id": "6a56259c09ffd97854d12065_1",
                      "name": "Chuối Già - HD2",
                      "remote_data": {
                        "url": "https://raw.githubusercontent.com/nghehoang007-wq/HFB321/main/stream/6a56259c09ffd97854d12065.json"
                      }
                    },
                    {
                      "id": "6a56259c09ffd97854d12065_2",
                      "name": "Chuối Già - FHD1",
                      "remote_data": {
                        "url": "https://raw.githubusercontent.com/nghehoang007-wq/HFB321/main/stream/6a56259c09ffd97854d12065.json"
                      }
                    },
                    {
                      "id": "6a56259c09ffd97854d12065_3",
                      "name": "Chuối Già - FHD2",
                      "remote_data": {
                        "url": "https://raw.githubusercontent.com/nghehoang007-wq/HFB321/main/stream/6a56259c09ffd97854d12065.json"
                      }
                    }
                  ]
                }
              ]
            }
          ]
        },
        {
          "id": "6a54648b09ffd97854a3e601",
          "name": "Leones del Norte vs Deportivo Cuenca",
          "labels": [
            {
              "position": "bottom-center",
              "text": "05h00",
              "color": "#FF0000",
              "text_color": "#FFFFFF"
            },
            {
              "position": "top-left",
              "text": "Leones del N..",
              "color": "#80000000",
              "text_color": "#FFFFFF"
            },
            {
              "position": "top-right",
              "text": "Deportivo Cu..",
              "color": "#80000000",
              "text_color": "#FFFFFF"
            }
          ],
          "image": {
            "url": "https://raw.githubusercontent.com/nghehoang007-wq/HFB321/main/thumbs/6a54648b09ffd97854a3e601.png",
            "height": 360,
            "width": 640,
            "display": "cover"
          },
          "type": "single",
          "display": "thumbnail-only",
          "sources": [
            {
              "id": "src-6a54648b09ffd97854a3e601",
              "name": "Chuối Chiên",
              "contents": [
                {
                  "id": "c-6a54648b09ffd97854a3e601",
                  "name": "Leones del Norte vs Deportivo Cuenca",
                  "streams": [
                    {
                      "id": "6a54648b09ffd97854a3e601_0",
                      "name": "Chuối Nhỏ - HD1",
                      "remote_data": {
                        "url": "https://raw.githubusercontent.com/nghehoang007-wq/HFB321/main/stream/6a54648b09ffd97854a3e601.json"
                      }
                    },
                    {
                      "id": "6a54648b09ffd97854a3e601_1",
                      "name": "Chuối Nhỏ - HD2",
                      "remote_data": {
                        "url": "https://raw.githubusercontent.com/nghehoang007-wq/HFB321/main/stream/6a54648b09ffd97854a3e601.json"
                      }
                    },
                    {
                      "id": "6a54648b09ffd97854a3e601_2",
                      "name": "Chuối Nhỏ - FHD1",
                      "remote_data": {
                        "url": "https://raw.githubusercontent.com/nghehoang007-wq/HFB321/main/stream/6a54648b09ffd97854a3e601.json"
                      }
                    },
                    {
                      "id": "6a54648b09ffd97854a3e601_3",
                      "name": "Chuối Nhỏ - FHD2",
                      "remote_data": {
                        "url": "https://raw.githubusercontent.com/nghehoang007-wq/HFB321/main/stream/6a54648b09ffd97854a3e601.json"
                      }
                    }
                  ]
                }
              ]
            }
          ]
        },
        {
          "id": "6a5464c409ffd97854a3eba8",
          "name": "Barcelona SC vs Guayaquil City FC",
          "labels": [
            {
              "position": "bottom-center",
              "text": "07h30",
              "color": "#FF0000",
              "text_color": "#FFFFFF"
            },
            {
              "position": "top-left",
              "text": "Barca",
              "color": "#80000000",
              "text_color": "#FFFFFF"
            },
            {
              "position": "top-right",
              "text": "Guayaquil Ci..",
              "color": "#80000000",
              "text_color": "#FFFFFF"
            }
          ],
          "image": {
            "url": "https://raw.githubusercontent.com/nghehoang007-wq/HFB321/main/thumbs/6a5464c409ffd97854a3eba8.png",
            "height": 360,
            "width": 640,
            "display": "cover"
          },
          "type": "single",
          "display": "thumbnail-only",
          "sources": [
            {
              "id": "src-6a5464c409ffd97854a3eba8",
              "name": "Chuối Chiên",
              "contents": [
                {
                  "id": "c-6a5464c409ffd97854a3eba8",
                  "name": "Barcelona SC vs Guayaquil City FC",
                  "streams": [
                    {
                      "id": "6a5464c409ffd97854a3eba8_0",
                      "name": "Trốc Tru - HD1",
                      "remote_data": {
                        "url": "https://raw.githubusercontent.com/nghehoang007-wq/HFB321/main/stream/6a5464c409ffd97854a3eba8.json"
                      }
                    },
                    {
                      "id": "6a5464c409ffd97854a3eba8_1",
                      "name": "Trốc Tru - HD2",
                      "remote_data": {
                        "url": "https://raw.githubusercontent.com/nghehoang007-wq/HFB321/main/stream/6a5464c409ffd97854a3eba8.json"
                      }
                    },
                    {
                      "id": "6a5464c409ffd97854a3eba8_2",
                      "name": "Trốc Tru - FHD1",
                      "remote_data": {
                        "url": "https://raw.githubusercontent.com/nghehoang007-wq/HFB321/main/stream/6a5464c409ffd97854a3eba8.json"
                      }
                    },
                    {
                      "id": "6a5464c409ffd97854a3eba8_3",
                      "name": "Trốc Tru - FHD2",
                      "remote_data": {
                        "url": "https://raw.githubusercontent.com/nghehoang007-wq/HFB321/main/stream/6a5464c409ffd97854a3eba8.json"
                      }
                    }
                  ]
                }
              ]
            }
          ]
        }
      ]
    }
  ],
  "notice": {
    "id": "notice",
    "link": "https://t.me",
    "icon": "https://raw.githubusercontent.com/nghehoang007-wq/HFB321/main/HFB/Thump/chuoichien.png",
    "closeable": true
  },
  "cache_time": 5,
  "option": {
    "save_history": true,
    "save_search_history": false,
    "save_wishlist": false
  }
}